neuralg/__init__.py
neuralg/evaluation/__init__.py
neuralg/evaluation/compare.py
neuralg/evaluation/compute_accuracy.py
neuralg/evaluation/evaluate.py
neuralg/evaluation/evaluate_model.py
neuralg/io/__init__.py
neuralg/io/download_models.py
neuralg/io/get_model.py
neuralg/io/load_custom_model.py
neuralg/io/load_model.py
neuralg/io/save_model.py
neuralg/models/__init__.py
neuralg/models/nerf.py
neuralg/ops/__init__.py
neuralg/ops/eigvals.py
neuralg/ops/svd.py
neuralg/ops/utils/__init__.py
neuralg/ops/utils/predict.py
neuralg/ops/utils/validate_input.py
neuralg/plots/__init__.py
neuralg/plots/plot_eigval_results.py
neuralg/plots/plot_loss_logs.py
neuralg/tests/ModelHandler_test.py
neuralg/tests/__init__.py
neuralg/tests/eigvals_test.py
neuralg/tests/get_model_test.py
neuralg/tests/io_test.py
neuralg/tests/svd_test.py
neuralg/tests/test_utils.py
neuralg/training/RandomMatrix.py
neuralg/training/RandomMatrixDataSet.py
neuralg/training/__init__.py
neuralg/training/get_sample.py
neuralg/training/load_default_training_cfg.py
neuralg/training/losses.py
neuralg/training/run_training.py
neuralg/training/save_run.py
neuralg/training/train_model.py
neuralg/training/train_models.py
neuralg/training/utils/__init__.py
neuralg/training/utils/sorting.py
neuralg/utils/ModelHandler.py
neuralg/utils/__init__.py
neuralg/utils/clear_loaded_models.py
neuralg/utils/constants.py
neuralg/utils/count_parameters.py
neuralg/utils/enable_cuda.py
neuralg/utils/print_cfg.py
neuralg/utils/set_log_level.py
neuralg/utils/set_precision.py
neuralg/utils/set_safe_mode.py
neuralg/utils/set_up_torch.py
neuralg-0.0.11.dist-info/LICENSE
neuralg-0.0.11.dist-info/METADATA
neuralg-0.0.11.dist-info/WHEEL
neuralg-0.0.11.dist-info/top_level.txt
neuralg-0.0.11.dist-info/RECORD
