Metadata-Version: 2.1
Name: neuralg
Version: 0.0.11
Summary: Package providing torch-based neural network approximators of linear algebra operations.
Home-page: https://github.com/esa/neuralg
Author: ESA Advanced Concepts Team
Author-email: toveag@kth.se
License: UNKNOWN
Project-URL: Source, https://github.com/esa/neuralg/
Platform: UNKNOWN
Classifier: Development Status :: 3 - Alpha
Classifier: Intended Audience :: Developers
Classifier: Intended Audience :: Science/Research
Classifier: Topic :: Scientific/Engineering :: Mathematics
Classifier: License :: OSI Approved :: GNU General Public License v3 (GPLv3)
Classifier: Programming Language :: Python :: 3.8
Requires-Python: >=3.8, <4
License-File: LICENSE
Requires-Dist: matplotlib (>=3.3.3)
Requires-Dist: torch (==1.9.0)
Requires-Dist: loguru (>=0.5.3)
Requires-Dist: dotmap (>=1.3.24)
Requires-Dist: toml (>=0.10.2)
Requires-Dist: requests (>=2.27.0)
